piplicenses.py
pip_licenses-5.0.0.dist-info/LICENSE
pip_licenses-5.0.0.dist-info/METADATA
pip_licenses-5.0.0.dist-info/WHEEL
pip_licenses-5.0.0.dist-info/entry_points.txt
pip_licenses-5.0.0.dist-info/top_level.txt
pip_licenses-5.0.0.dist-info/RECORD
