Metadata-Version: 2.1
Name: pip-licenses
Version: 5.0.0
Summary: Dump the software license list of Python packages installed with pip.
Author-email: raimon <raimon49@hotmail.com>
License: MIT
Project-URL: Homepage, https://github.com/raimon49/pip-licenses
Project-URL: Releases, https://github.com/raimon49/pip-licenses/releases
Project-URL: Issues, https://github.com/raimon49/pip-licenses/issues
Keywords: pip,pypi,package,license,check
Classifier: Development Status :: 5 - Production/Stable
Classifier: Intended Audience :: Developers
Classifier: License :: OSI Approved :: MIT License
Classifier: Programming Language :: Python :: 3
Classifier: Programming Language :: Python :: 3 :: Only
Classifier: Programming Language :: Python :: 3.9
Classifier: Programming Language :: Python :: 3.10
Classifier: Programming Language :: Python :: 3.11
Classifier: Programming Language :: Python :: 3.12
Classifier: Topic :: System :: Systems Administration
Classifier: Topic :: System :: System Shells
Classifier: Typing :: Typed
Requires-Python: >=3.9
License-File: LICENSE
Requires-Dist: prettytable>=2.3.0
Requires-Dist: tomli>=2
Provides-Extra: dev
Requires-Dist: autopep8; extra == "dev"
Requires-Dist: black; extra == "dev"
Requires-Dist: docutils; extra == "dev"
Requires-Dist: isort; extra == "dev"
Requires-Dist: wheel; extra == "dev"
Requires-Dist: mypy; extra == "dev"
Requires-Dist: pip-tools; extra == "dev"
Requires-Dist: pypandoc; extra == "dev"
Requires-Dist: pytest-cov; extra == "dev"
Requires-Dist: pytest-pycodestyle; extra == "dev"
Requires-Dist: pytest-runner; extra == "dev"
Requires-Dist: twine; extra == "dev"
Requires-Dist: tomli-w; extra == "dev"
